<Display Version="1.0">
  <Languages>
    <Language Name="0410">
      <StringTable>
        <String Name="IPText">Indirizzo IP</String>
        <String Name="BatteryText">Stato batteria</String>
        <String Name="FreeStorageText">Spazio libero</String>
        <String Name="SystemStorageText">Spazio sistema</String>
        <String Name="FreeMemoryText">Memoria libera</String>
        <String Name="SystemMemoryText">Memoria sistema </String>
        <String Name="ProcessorTypeText">Tipo procesador</String>
        <String Name="ComputerNameText">Nombre computadora</String>
        <String Name="TerminalTitleText">Info terminale</String>
        <String Name="BatteryChargeText">Caricamento</String>
        <String Name="OkButtonText">OK</String>
      </StringTable>
    </Language>
  </Languages>
</Display>